README.md
setup.py
falib/__init__.py
falib/aucvol2aucvol_today2yes.py
falib/aucvol2maxvol_today2yes.py
falib/beta.py
falib/concept_rise_ratio.py
falib/cross_n_min_amount.py
falib/cross_n_min_vol.py
falib/first_time_section.py
falib/firstcrosstime.py
falib/is_price_peak.py
falib/last_time_section.py
falib/ln_hl.py
falib/lowratio.py
falib/ma_day_rise_ratio.py
falib/macd.py
falib/macd_adj.py
falib/market_pearson_adj.py
falib/max_vol.py
falib/min_bomb_time.py
falib/n_cross_time.py
falib/net_inflow_rate_volume.py
falib/net_inflow_rate_volume_l.py
falib/o2c_today2yes.py
falib/rise_speed_n_min.py
falib/riseover_amount.py
falib/riseover_continue.py
falib/riseovernum_nday.py
falib/riseovernum_sector.py
falib/riseoverstock_bias_ma.py
falib/riseratio_sector.py
falib/s_li_largebuyrate.py
falib/s_risk_glvarianceratio.py
falib/s_tech_cyf.py
falib/s_tech_dhilo.py
falib/s_tech_rank.py
falib/s_tech_revs.py
falib/s_tech_rvi.py
falib/s_tech_volumn.py
falib/turn_over_ratio2MA5.py
falib/turnover_sector.py
falib/value_diff_institute.py
falib/volume_ratio.py
falib.egg-info/PKG-INFO
falib.egg-info/SOURCES.txt
falib.egg-info/dependency_links.txt
falib.egg-info/top_level.txt