Metadata-Version: 2.1
Name: falib
Version: 0.0.4
Summary: calculate quant factor
Home-page: https://gitee.com/jiangwenhao123/falib.git
Author: zuel_quant_lab
Author-email: 505871220@qq.com
License: UNKNOWN
Platform: UNKNOWN
Classifier: Programming Language :: Python :: 3
Classifier: License :: OSI Approved :: MIT License
Classifier: Operating System :: OS Independent
Requires-Python: >=3.6
